otds/__init__.py
otds/enums.py
otds/main.py
otds/py.typed
otds/typedefs.py
otds/schema/.DS_Store
otds/schema/otds-booking-merlin.xsd
otds/schema/otds-booking-toma.xsd
otds/schema/otds-schema-accommodation.xsd
otds/schema/otds-schema-addon.xsd
otds/schema/otds-schema-common.xsd
otds/schema/otds-schema-flight.xsd
otds/schema/otds-schema-products.xsd
otds/schema/otds.xsd
otds-0.0.1a5.dist-info/LICENSE
otds-0.0.1a5.dist-info/METADATA
otds-0.0.1a5.dist-info/WHEEL
otds-0.0.1a5.dist-info/top_level.txt
otds-0.0.1a5.dist-info/RECORD
